pyocc/__init__.py
pyocc/__main__.py
pyocc/pyocc.py
pyocc-0.0.3.dist-info/METADATA
pyocc-0.0.3.dist-info/RECORD
pyocc-0.0.3.dist-info/WHEEL
pyocc-0.0.3.dist-info/entry_points.txt
pyocc-0.0.3.dist-info/top_level.txt
tests/__init__.py
tests/test_pyocc.py
