Metadata-Version: 2.1
Name: pyocc
Version: 0.0.3
Summary: A wrapper for OpenCC (The Chinese convert solution)
Home-page: https://github.com/starofrainnight/pyocc
Author: Hong-She Liang
Author-email: starofrainnight@gmail.com
License: Apache Software License
Keywords: pyocc
Platform: UNKNOWN
Classifier: Development Status :: 2 - Pre-Alpha
Classifier: Intended Audience :: Developers
Classifier: License :: OSI Approved :: Apache Software License
Classifier: Natural Language :: English
Classifier: Programming Language :: Python :: 3
Classifier: Programming Language :: Python :: 3.4
Classifier: Programming Language :: Python :: 3.5
Classifier: Programming Language :: Python :: 3.6
Requires-Dist: click (>=6.0)
Requires-Dist: whichcraft
